rc/__init__.py
rc/cache.py
rc/ketama.py
rc/poller.py
rc/promise.py
rc/redis_clients.py
rc/redis_cluster.py
rc/redis_router.py
rc/serializer.py
rc/testing.py
rc/utils.py
rc-0.3.1.dist-info/DESCRIPTION.rst
rc-0.3.1.dist-info/METADATA
rc-0.3.1.dist-info/metadata.json
rc-0.3.1.dist-info/RECORD
rc-0.3.1.dist-info/top_level.txt
rc-0.3.1.dist-info/WHEEL
