Metadata-Version: 2.0
Name: rc
Version: 0.3.1
Summary: rc, the redis cache
Home-page: http://github.com/fengsp/rc
Author: Shipeng Feng
Author-email: fsp261@gmail.com
License: UNKNOWN
Platform: UNKNOWN
Classifier: License :: OSI Approved :: BSD License
Classifier: Programming Language :: Python
Classifier: Programming Language :: Python :: 2
Requires-Dist: redis (>=2.6)
